test_gabrielgavrilov/__init__.py
test_gabrielgavrilov/mocha.py
test_gabrielgavrilov/mocha_client.py
test_gabrielgavrilov/mocha_parser.py
test_gabrielgavrilov/mocha_request.py
test_gabrielgavrilov/mocha_response.py
test_gabrielgavrilov-0.0.1.dist-info/LICENSE
test_gabrielgavrilov-0.0.1.dist-info/METADATA
test_gabrielgavrilov-0.0.1.dist-info/WHEEL
test_gabrielgavrilov-0.0.1.dist-info/top_level.txt
test_gabrielgavrilov-0.0.1.dist-info/RECORD
