Metadata-Version: 2.1
Name: test_gabrielgavrilov
Version: 0.0.1
Summary: A python test package
Author-email: Gabriel Gavrilov <gabriel.gavrilov02@gmail.com>
Classifier: Programming Language :: Python :: 3
Classifier: License :: OSI Approved :: MIT License
Classifier: Operating System :: OS Independent
Requires-Python: >=3.8
License-File: LICENSE
